contourvision/__init__.py
contourvision/video_processor.py
contourvision-0.1.8.dist-info/licenses/LICENSE
contourvision-0.1.8.dist-info/METADATA
contourvision-0.1.8.dist-info/WHEEL
contourvision-0.1.8.dist-info/top_level.txt
contourvision-0.1.8.dist-info/RECORD
