Metadata-Version: 2.4
Name: contourvision
Version: 0.1.8
Summary: A Python tool for extracting and visualizing contours in videos using various thresholding methods.
Home-page: https://github.com/viliusbankauskas/contourvision
Author: Vilius Bankauskas
Author-email: bankauskasvil@gmail.com
License: MIT
Project-URL: Bug Tracker, https://github.com/viliusbankauskas/contourvision/issues
Project-URL: Documentation, https://github.com/viliusbankauskas/contourvision/blob/main/README.md
Project-URL: Source Code, https://github.com/viliusbankauskas/contourvision
Classifier: Development Status :: 3 - Alpha
Classifier: Intended Audience :: Developers
Classifier: Intended Audience :: Education
Classifier: Intended Audience :: Science/Research
Classifier: License :: OSI Approved :: MIT License
Classifier: Programming Language :: Python :: 3
Classifier: Programming Language :: Python :: 3.8
Classifier: Programming Language :: Python :: 3.9
Classifier: Programming Language :: Python :: 3.10
Classifier: Programming Language :: Python :: 3.11
Classifier: Programming Language :: Python :: 3.12
Classifier: Operating System :: OS Independent
Classifier: Topic :: Software Development :: Libraries :: Python Modules
Classifier: Topic :: Multimedia :: Video
Classifier: Topic :: Scientific/Engineering :: Image Processing
Classifier: Topic :: Utilities
Requires-Python: >=3.8
License-File: LICENSE
Requires-Dist: opencv-python>=4.0
Requires-Dist: numpy>=1.19
Dynamic: author
Dynamic: author-email
Dynamic: classifier
Dynamic: description
Dynamic: description-content-type
Dynamic: home-page
Dynamic: license
Dynamic: license-file
Dynamic: project-url
Dynamic: requires-dist
Dynamic: requires-python
Dynamic: summary
